{
  "resourceType" : "ValueSet",
  "id" : "VSLocalizationMethod",
  "text" : {
    "status" : "generated",
    "div" : "<div xmlns=\"http://www.w3.org/1999/xhtml\"><p class=\"res-header-id\"><b>Generated Narrative: ValueSet VSLocalizationMethod</b></p><a name=\"VSLocalizationMethod\"> </a><a name=\"hcVSLocalizationMethod\"> </a><a name=\"VSLocalizationMethod-en-US\"> </a><p>This value set includes codes based on the following rules:</p><ul/></div>"
  },
  "url" : "https://ig-osiris.cancer.fr/ig/osiris/ValueSet/VSLocalizationMethod",
  "version" : "1.1.0",
  "name" : "VSLocalizationMethod",
  "title" : "Localization Method Value Set",
  "status" : "draft",
  "date" : "2025-04-22T15:20:25+00:00",
  "publisher" : "institutcancer",
  "contact" : [{
    "name" : "institutcancer",
    "telecom" : [{
      "system" : "url",
      "value" : "http://cancer.fr"
    },
    {
      "system" : "email",
      "value" : "osiris@institutcancer.fr"
    }]
  },
  {
    "name" : "Aurélien JOBARD",
    "telecom" : [{
      "system" : "email",
      "value" : "osiris@institutcancer.fr"
    }]
  }],
  "description" : "Localization Method"
}